[
{
  "name":"boolean[]"
},
{
  "name":"byte[]"
},
{
  "name":"ch.qos.logback.classic.encoder.PatternLayoutEncoder",
  "allPublicMethods":true,
  "methods":[{"name":"<init>","parameterTypes":[] }]
},
{
  "name":"ch.qos.logback.classic.pattern.DateConverter",
  "methods":[{"name":"<init>","parameterTypes":[] }]
},
{
  "name":"ch.qos.logback.classic.pattern.LevelConverter",
  "methods":[{"name":"<init>","parameterTypes":[] }]
},
{
  "name":"ch.qos.logback.classic.pattern.LineOfCallerConverter",
  "methods":[{"name":"<init>","parameterTypes":[] }]
},
{
  "name":"ch.qos.logback.classic.pattern.LineSeparatorConverter",
  "methods":[{"name":"<init>","parameterTypes":[] }]
},
{
  "name":"ch.qos.logback.classic.pattern.LoggerConverter",
  "methods":[{"name":"<init>","parameterTypes":[] }]
},
{
  "name":"ch.qos.logback.classic.pattern.MessageConverter",
  "methods":[{"name":"<init>","parameterTypes":[] }]
},
{
  "name":"ch.qos.logback.classic.pattern.MethodOfCallerConverter",
  "methods":[{"name":"<init>","parameterTypes":[] }]
},
{
  "name":"ch.qos.logback.classic.pattern.ThreadConverter",
  "methods":[{"name":"<init>","parameterTypes":[] }]
},
{
  "name":"ch.qos.logback.classic.pattern.color.HighlightingCompositeConverter",
  "methods":[{"name":"<init>","parameterTypes":[] }]
},
{
  "name":"ch.qos.logback.core.ConsoleAppender",
  "allPublicMethods":true,
  "methods":[{"name":"<init>","parameterTypes":[] }]
},
{
  "name":"ch.qos.logback.core.pattern.color.CyanCompositeConverter",
  "methods":[{"name":"<init>","parameterTypes":[] }]
},
{
  "name":"ch.qos.logback.core.pattern.color.GreenCompositeConverter",
  "methods":[{"name":"<init>","parameterTypes":[] }]
},
{
  "name":"char[]"
},
{
  "name":"com.sun.jndi.dns.DnsContextFactory",
  "methods":[{"name":"<init>","parameterTypes":[] }]
},
{
  "name":"com.sun.management.GarbageCollectorMXBean",
  "allPublicMethods":true
},
{
  "name":"com.sun.management.GcInfo",
  "allPublicMethods":true
},
{
  "name":"com.sun.management.HotSpotDiagnosticMXBean",
  "allPublicMethods":true
},
{
  "name":"com.sun.management.ThreadMXBean",
  "allPublicMethods":true
},
{
  "name":"com.sun.management.UnixOperatingSystemMXBean",
  "allPublicMethods":true
},
{
  "name":"com.sun.management.VMOption",
  "allPublicMethods":true
},
{
  "name":"com.sun.org.apache.xerces.internal.jaxp.SAXParserFactoryImpl",
  "methods":[{"name":"<init>","parameterTypes":[] }]
},
{
  "name":"double[]"
},
{
  "name":"float[]"
},
{
  "name":"int[]"
},
{
  "name":"io.netty.buffer.AbstractByteBufAllocator",
  "allDeclaredMethods":true
},
{
  "name":"io.netty.buffer.AbstractReferenceCountedByteBuf",
  "fields":[{"name":"refCnt", "allowUnsafeAccess":true}]
},
{
  "name":"io.netty.channel.ChannelDuplexHandler",
  "methods":[
    {"name":"bind","parameterTypes":["io.netty.channel.ChannelHandlerContext","java.net.SocketAddress","io.netty.channel.ChannelPromise"] }, 
    {"name":"connect","parameterTypes":["io.netty.channel.ChannelHandlerContext","java.net.SocketAddress","java.net.SocketAddress","io.netty.channel.ChannelPromise"] }, 
    {"name":"deregister","parameterTypes":["io.netty.channel.ChannelHandlerContext","io.netty.channel.ChannelPromise"] }, 
    {"name":"disconnect","parameterTypes":["io.netty.channel.ChannelHandlerContext","io.netty.channel.ChannelPromise"] }, 
    {"name":"flush","parameterTypes":["io.netty.channel.ChannelHandlerContext"] }, 
    {"name":"read","parameterTypes":["io.netty.channel.ChannelHandlerContext"] }, 
    {"name":"write","parameterTypes":["io.netty.channel.ChannelHandlerContext","java.lang.Object","io.netty.channel.ChannelPromise"] }
  ]
},
{
  "name":"io.netty.channel.ChannelHandlerAdapter",
  "methods":[{"name":"exceptionCaught","parameterTypes":["io.netty.channel.ChannelHandlerContext","java.lang.Throwable"] }]
},
{
  "name":"io.netty.channel.ChannelInboundHandlerAdapter",
  "methods":[
    {"name":"channelActive","parameterTypes":["io.netty.channel.ChannelHandlerContext"] }, 
    {"name":"channelInactive","parameterTypes":["io.netty.channel.ChannelHandlerContext"] }, 
    {"name":"channelRead","parameterTypes":["io.netty.channel.ChannelHandlerContext","java.lang.Object"] }, 
    {"name":"channelReadComplete","parameterTypes":["io.netty.channel.ChannelHandlerContext"] }, 
    {"name":"channelRegistered","parameterTypes":["io.netty.channel.ChannelHandlerContext"] }, 
    {"name":"channelUnregistered","parameterTypes":["io.netty.channel.ChannelHandlerContext"] }, 
    {"name":"channelWritabilityChanged","parameterTypes":["io.netty.channel.ChannelHandlerContext"] }, 
    {"name":"exceptionCaught","parameterTypes":["io.netty.channel.ChannelHandlerContext","java.lang.Throwable"] }, 
    {"name":"userEventTriggered","parameterTypes":["io.netty.channel.ChannelHandlerContext","java.lang.Object"] }
  ]
},
{
  "name":"io.netty.channel.ChannelInitializer",
  "methods":[
    {"name":"channelRegistered","parameterTypes":["io.netty.channel.ChannelHandlerContext"] }, 
    {"name":"exceptionCaught","parameterTypes":["io.netty.channel.ChannelHandlerContext","java.lang.Throwable"] }
  ]
},
{
  "name":"io.netty.channel.ChannelOutboundHandlerAdapter",
  "methods":[
    {"name":"bind","parameterTypes":["io.netty.channel.ChannelHandlerContext","java.net.SocketAddress","io.netty.channel.ChannelPromise"] }, 
    {"name":"close","parameterTypes":["io.netty.channel.ChannelHandlerContext","io.netty.channel.ChannelPromise"] }, 
    {"name":"connect","parameterTypes":["io.netty.channel.ChannelHandlerContext","java.net.SocketAddress","java.net.SocketAddress","io.netty.channel.ChannelPromise"] }, 
    {"name":"deregister","parameterTypes":["io.netty.channel.ChannelHandlerContext","io.netty.channel.ChannelPromise"] }, 
    {"name":"disconnect","parameterTypes":["io.netty.channel.ChannelHandlerContext","io.netty.channel.ChannelPromise"] }, 
    {"name":"flush","parameterTypes":["io.netty.channel.ChannelHandlerContext"] }, 
    {"name":"read","parameterTypes":["io.netty.channel.ChannelHandlerContext"] }
  ]
},
{
  "name":"io.netty.channel.DefaultChannelPipeline$HeadContext",
  "methods":[
    {"name":"bind","parameterTypes":["io.netty.channel.ChannelHandlerContext","java.net.SocketAddress","io.netty.channel.ChannelPromise"] }, 
    {"name":"channelActive","parameterTypes":["io.netty.channel.ChannelHandlerContext"] }, 
    {"name":"channelInactive","parameterTypes":["io.netty.channel.ChannelHandlerContext"] }, 
    {"name":"channelRead","parameterTypes":["io.netty.channel.ChannelHandlerContext","java.lang.Object"] }, 
    {"name":"channelReadComplete","parameterTypes":["io.netty.channel.ChannelHandlerContext"] }, 
    {"name":"channelRegistered","parameterTypes":["io.netty.channel.ChannelHandlerContext"] }, 
    {"name":"channelUnregistered","parameterTypes":["io.netty.channel.ChannelHandlerContext"] }, 
    {"name":"channelWritabilityChanged","parameterTypes":["io.netty.channel.ChannelHandlerContext"] }, 
    {"name":"close","parameterTypes":["io.netty.channel.ChannelHandlerContext","io.netty.channel.ChannelPromise"] }, 
    {"name":"connect","parameterTypes":["io.netty.channel.ChannelHandlerContext","java.net.SocketAddress","java.net.SocketAddress","io.netty.channel.ChannelPromise"] }, 
    {"name":"deregister","parameterTypes":["io.netty.channel.ChannelHandlerContext","io.netty.channel.ChannelPromise"] }, 
    {"name":"disconnect","parameterTypes":["io.netty.channel.ChannelHandlerContext","io.netty.channel.ChannelPromise"] }, 
    {"name":"exceptionCaught","parameterTypes":["io.netty.channel.ChannelHandlerContext","java.lang.Throwable"] }, 
    {"name":"flush","parameterTypes":["io.netty.channel.ChannelHandlerContext"] }, 
    {"name":"read","parameterTypes":["io.netty.channel.ChannelHandlerContext"] }, 
    {"name":"userEventTriggered","parameterTypes":["io.netty.channel.ChannelHandlerContext","java.lang.Object"] }, 
    {"name":"write","parameterTypes":["io.netty.channel.ChannelHandlerContext","java.lang.Object","io.netty.channel.ChannelPromise"] }
  ]
},
{
  "name":"io.netty.channel.DefaultChannelPipeline$TailContext",
  "methods":[
    {"name":"channelActive","parameterTypes":["io.netty.channel.ChannelHandlerContext"] }, 
    {"name":"channelInactive","parameterTypes":["io.netty.channel.ChannelHandlerContext"] }, 
    {"name":"channelRead","parameterTypes":["io.netty.channel.ChannelHandlerContext","java.lang.Object"] }, 
    {"name":"channelReadComplete","parameterTypes":["io.netty.channel.ChannelHandlerContext"] }, 
    {"name":"channelRegistered","parameterTypes":["io.netty.channel.ChannelHandlerContext"] }, 
    {"name":"channelUnregistered","parameterTypes":["io.netty.channel.ChannelHandlerContext"] }, 
    {"name":"channelWritabilityChanged","parameterTypes":["io.netty.channel.ChannelHandlerContext"] }, 
    {"name":"exceptionCaught","parameterTypes":["io.netty.channel.ChannelHandlerContext","java.lang.Throwable"] }, 
    {"name":"userEventTriggered","parameterTypes":["io.netty.channel.ChannelHandlerContext","java.lang.Object"] }
  ]
},
{
  "name":"io.netty.handler.codec.MessageToMessageDecoder",
  "methods":[{"name":"channelRead","parameterTypes":["io.netty.channel.ChannelHandlerContext","java.lang.Object"] }]
},
{
  "name":"io.netty.handler.codec.MessageToMessageEncoder",
  "methods":[{"name":"write","parameterTypes":["io.netty.channel.ChannelHandlerContext","java.lang.Object","io.netty.channel.ChannelPromise"] }]
},
{
  "name":"io.netty.handler.codec.dns.DatagramDnsQueryEncoder"
},
{
  "name":"io.netty.resolver.dns.DnsNameResolver$1"
},
{
  "name":"io.netty.resolver.dns.DnsNameResolver$3"
},
{
  "name":"io.netty.resolver.dns.DnsNameResolver$DnsResponseHandler",
  "methods":[
    {"name":"channelActive","parameterTypes":["io.netty.channel.ChannelHandlerContext"] }, 
    {"name":"channelRead","parameterTypes":["io.netty.channel.ChannelHandlerContext","java.lang.Object"] }, 
    {"name":"exceptionCaught","parameterTypes":["io.netty.channel.ChannelHandlerContext","java.lang.Throwable"] }
  ]
},
{
  "name":"io.netty.util.ReferenceCountUtil",
  "allDeclaredMethods":true
},
{
  "name":"io.netty.util.internal.shaded.org.jctools.queues.BaseMpscLinkedArrayQueueColdProducerFields",
  "fields":[{"name":"producerLimit", "allowUnsafeAccess":true}]
},
{
  "name":"io.netty.util.internal.shaded.org.jctools.queues.BaseMpscLinkedArrayQueueConsumerFields",
  "fields":[{"name":"consumerIndex", "allowUnsafeAccess":true}]
},
{
  "name":"io.netty.util.internal.shaded.org.jctools.queues.BaseMpscLinkedArrayQueueProducerFields",
  "fields":[{"name":"producerIndex", "allowUnsafeAccess":true}]
},
{
  "name":"io.netty.util.internal.shaded.org.jctools.queues.MpscArrayQueueConsumerIndexField",
  "fields":[{"name":"consumerIndex", "allowUnsafeAccess":true}]
},
{
  "name":"io.netty.util.internal.shaded.org.jctools.queues.MpscArrayQueueProducerIndexField",
  "fields":[{"name":"producerIndex", "allowUnsafeAccess":true}]
},
{
  "name":"io.netty.util.internal.shaded.org.jctools.queues.MpscArrayQueueProducerLimitField",
  "fields":[{"name":"producerLimit", "allowUnsafeAccess":true}]
},
{
  "name":"io.vertx.core.logging.SLF4JLogDelegateFactory",
  "methods":[{"name":"<init>","parameterTypes":[] }]
},
{
  "name":"io.vertx.core.net.impl.VertxHandler",
  "methods":[
    {"name":"channelInactive","parameterTypes":["io.netty.channel.ChannelHandlerContext"] }, 
    {"name":"channelRead","parameterTypes":["io.netty.channel.ChannelHandlerContext","java.lang.Object"] }, 
    {"name":"channelReadComplete","parameterTypes":["io.netty.channel.ChannelHandlerContext"] }, 
    {"name":"channelWritabilityChanged","parameterTypes":["io.netty.channel.ChannelHandlerContext"] }, 
    {"name":"close","parameterTypes":["io.netty.channel.ChannelHandlerContext","io.netty.channel.ChannelPromise"] }, 
    {"name":"exceptionCaught","parameterTypes":["io.netty.channel.ChannelHandlerContext","java.lang.Throwable"] }, 
    {"name":"userEventTriggered","parameterTypes":["io.netty.channel.ChannelHandlerContext","java.lang.Object"] }
  ]
},
{
  "name":"java.lang.Boolean",
  "fields":[{"name":"TYPE"}]
},
{
  "name":"java.lang.Byte",
  "fields":[{"name":"TYPE"}]
},
{
  "name":"java.lang.Character",
  "fields":[{"name":"TYPE"}]
},
{
  "name":"java.lang.Double",
  "fields":[{"name":"TYPE"}]
},
{
  "name":"java.lang.Float",
  "fields":[{"name":"TYPE"}]
},
{
  "name":"java.lang.Integer",
  "fields":[{"name":"TYPE"}]
},
{
  "name":"java.lang.Long",
  "fields":[{"name":"TYPE"}]
},
{
  "name":"java.lang.RuntimePermission"
},
{
  "name":"java.lang.Short",
  "fields":[{"name":"TYPE"}]
},
{
  "name":"java.lang.StackTraceElement",
  "allPublicMethods":true
},
{
  "name":"java.lang.String"
},
{
  "name":"java.lang.String[]"
},
{
  "name":"java.lang.Void",
  "fields":[{"name":"TYPE"}]
},
{
  "name":"java.lang.management.BufferPoolMXBean",
  "allPublicMethods":true
},
{
  "name":"java.lang.management.ClassLoadingMXBean",
  "allPublicMethods":true
},
{
  "name":"java.lang.management.CompilationMXBean",
  "allPublicMethods":true
},
{
  "name":"java.lang.management.LockInfo",
  "allPublicMethods":true
},
{
  "name":"java.lang.management.ManagementFactory",
  "methods":[{"name":"getRuntimeMXBean","parameterTypes":[] }]
},
{
  "name":"java.lang.management.ManagementPermission",
  "methods":[{"name":"<init>","parameterTypes":["java.lang.String"] }]
},
{
  "name":"java.lang.management.MemoryMXBean",
  "allPublicMethods":true
},
{
  "name":"java.lang.management.MemoryManagerMXBean",
  "allPublicMethods":true
},
{
  "name":"java.lang.management.MemoryPoolMXBean",
  "allPublicMethods":true
},
{
  "name":"java.lang.management.MemoryUsage",
  "allPublicMethods":true
},
{
  "name":"java.lang.management.MonitorInfo",
  "allPublicMethods":true
},
{
  "name":"java.lang.management.RuntimeMXBean",
  "allPublicMethods":true
},
{
  "name":"java.lang.management.ThreadInfo",
  "allPublicMethods":true
},
{
  "name":"java.math.BigDecimal"
},
{
  "name":"java.math.BigInteger"
},
{
  "name":"java.net.SocketOption"
},
{
  "name":"java.net.SocketPermission"
},
{
  "name":"java.net.StandardSocketOptions",
  "fields":[
    {"name":"IP_MULTICAST_IF"}, 
    {"name":"IP_MULTICAST_LOOP"}, 
    {"name":"IP_MULTICAST_TTL"}
  ]
},
{
  "name":"java.nio.Bits",
  "methods":[{"name":"unaligned","parameterTypes":[] }]
},
{
  "name":"java.nio.Buffer",
  "fields":[{"name":"address", "allowUnsafeAccess":true}]
},
{
  "name":"java.nio.DirectByteBuffer",
  "fields":[{"name":"cleaner", "allowUnsafeAccess":true}],
  "methods":[{"name":"<init>","parameterTypes":["long","int"] }]
},
{
  "name":"java.nio.channels.NetworkChannel",
  "methods":[
    {"name":"getOption","parameterTypes":["java.net.SocketOption"] }, 
    {"name":"setOption","parameterTypes":["java.net.SocketOption","java.lang.Object"] }
  ]
},
{
  "name":"java.security.AllPermission"
},
{
  "name":"java.security.MessageDigestSpi"
},
{
  "name":"java.util.Date"
},
{
  "name":"java.util.PropertyPermission",
  "methods":[{"name":"<init>","parameterTypes":["java.lang.String","java.lang.String"] }]
},
{
  "name":"javax.management.MBeanOperationInfo",
  "allPublicMethods":true
},
{
  "name":"javax.management.MBeanServerBuilder",
  "methods":[{"name":"<init>","parameterTypes":[] }]
},
{
  "name":"javax.management.ObjectName"
},
{
  "name":"javax.management.openmbean.CompositeData"
},
{
  "name":"javax.management.openmbean.CompositeData[]"
},
{
  "name":"javax.management.openmbean.OpenMBeanOperationInfoSupport"
},
{
  "name":"javax.management.openmbean.TabularData"
},
{
  "name":"jdk.Exported",
  "allPublicMethods":true
},
{
  "name":"jdk.management.jfr.ConfigurationInfo",
  "allPublicMethods":true
},
{
  "name":"jdk.management.jfr.EventTypeInfo",
  "allPublicMethods":true
},
{
  "name":"jdk.management.jfr.FlightRecorderMXBean",
  "allPublicMethods":true
},
{
  "name":"jdk.management.jfr.FlightRecorderMXBeanImpl",
  "allPublicConstructors":true
},
{
  "name":"jdk.management.jfr.RecordingInfo",
  "allPublicMethods":true
},
{
  "name":"jdk.management.jfr.SettingDescriptorInfo",
  "allPublicMethods":true
},
{
  "name":"jdk.management.jfr.internal.FlightRecorderMXBeanProvider",
  "methods":[{"name":"getFlightRecorderMXBean","parameterTypes":[] }]
},
{
  "name":"long[]"
},
{
  "name":"org.apache.commons.pool2.impl.DefaultEvictionPolicy",
  "methods":[{"name":"<init>","parameterTypes":[] }]
},
{
  "name":"org.apache.commons.pool2.impl.DefaultPooledObjectInfo",
  "allPublicMethods":true
},
{
  "name":"org.apache.commons.pool2.impl.GenericObjectPool",
  "allPublicConstructors":true
},
{
  "name":"org.apache.commons.pool2.impl.GenericObjectPoolMXBean",
  "allPublicMethods":true
},
{
  "name":"org.graalvm.compiler.hotspot.management.AggregatedMemoryPoolBean",
  "allPublicConstructors":true
},
{
  "name":"short[]"
},
{
  "name":"sun.management.ClassLoadingImpl",
  "allPublicConstructors":true
},
{
  "name":"sun.management.CompilationImpl",
  "allPublicConstructors":true
},
{
  "name":"sun.management.GarbageCollectorImpl",
  "allPublicConstructors":true
},
{
  "name":"sun.management.HotSpotDiagnostic",
  "allPublicConstructors":true
},
{
  "name":"sun.management.ManagementFactoryHelper$1",
  "allPublicConstructors":true
},
{
  "name":"sun.management.ManagementFactoryHelper$LoggingMXBean",
  "allPublicMethods":true
},
{
  "name":"sun.management.ManagementFactoryHelper$PlatformLoggingImpl",
  "allPublicConstructors":true
},
{
  "name":"sun.management.MemoryImpl",
  "allPublicConstructors":true
},
{
  "name":"sun.management.MemoryManagerImpl",
  "allPublicConstructors":true
},
{
  "name":"sun.management.MemoryPoolImpl",
  "allPublicConstructors":true
},
{
  "name":"sun.management.OperatingSystemImpl",
  "allPublicConstructors":true
},
{
  "name":"sun.management.RuntimeImpl",
  "allPublicConstructors":true
},
{
  "name":"sun.management.ThreadImpl",
  "allPublicConstructors":true
},
{
  "name":"sun.misc.Cleaner",
  "methods":[{"name":"clean","parameterTypes":[] }]
},
{
  "name":"sun.misc.Unsafe",
  "fields":[{"name":"theUnsafe"}],
  "methods":[
    {"name":"copyMemory","parameterTypes":["java.lang.Object","long","java.lang.Object","long","long"] }, 
    {"name":"getAndAddLong","parameterTypes":["java.lang.Object","long","long"] }, 
    {"name":"getAndSetObject","parameterTypes":["java.lang.Object","long","java.lang.Object"] }
  ]
},
{
  "name":"sun.misc.VM",
  "methods":[{"name":"maxDirectMemory","parameterTypes":[] }]
},
{
  "name":"sun.nio.ch.SelectorImpl",
  "fields":[
    {"name":"publicSelectedKeys"}, 
    {"name":"selectedKeys"}
  ]
},
{
  "name":"sun.security.provider.NativePRNG",
  "methods":[{"name":"<init>","parameterTypes":[] }]
},
{
  "name":"sun.security.provider.PolicyFile",
  "methods":[{"name":"<init>","parameterTypes":[] }]
},
{
  "name":"sun.security.provider.SHA",
  "methods":[{"name":"<init>","parameterTypes":[] }]
},
{
  "name":"sun.security.provider.Sun",
  "methods":[{"name":"<init>","parameterTypes":[] }]
}
]
